usbmon_exporter/__init__.py
usbmon_exporter/_app.py
usbmon_exporter/_exporter.py
usbmon_exporter/_metrics.py
usbmon_exporter/_sysfs.py
usbmon_exporter/_uevent.py
usbmon_exporter/_usbmon.py
usbmon_exporter-0.1.0.dist-info/licenses/LICENSE.txt
usbmon_exporter-0.1.0.dist-info/METADATA
usbmon_exporter-0.1.0.dist-info/WHEEL
usbmon_exporter-0.1.0.dist-info/entry_points.txt
usbmon_exporter-0.1.0.dist-info/top_level.txt
usbmon_exporter-0.1.0.dist-info/RECORD
