Metadata-Version: 2.4
Name: usbmon-exporter
Version: 0.1.0
Summary: Prometheus exporter for usbmon
Author-email: Simon Holesch <simon@holesch.de>
License-Expression: MIT
Project-URL: Issues, https://github.com/holesch/usbmon-exporter/issues
Project-URL: Source, https://github.com/holesch/usbmon-exporter
Keywords: prometheus,grafana,usbmon
Classifier: Development Status :: 4 - Beta
Classifier: Environment :: Console
Classifier: Intended Audience :: Developers
Classifier: Operating System :: POSIX :: Linux
Classifier: Programming Language :: Python
Classifier: Programming Language :: Python :: 3.10
Classifier: Programming Language :: Python :: 3.11
Classifier: Programming Language :: Python :: 3.12
Classifier: Programming Language :: Python :: 3.13
Classifier: Programming Language :: Python :: 3.14
Classifier: Topic :: System :: Hardware :: Universal Serial Bus (USB)
Classifier: Topic :: System :: Monitoring
Requires-Python: >=3.10
License-File: LICENSE.txt
Requires-Dist: prometheus-client
Dynamic: license-file
